{
   "docker":{
      "major":{
         "enabled":true
      },
      "pinDigests":true
   },
   "docker-compose":{
      "fileMatch":[
         "(^|/)(stack|production)[^/]*\\.ya?ml$"
      ],
      "digest": {
        "enabled": false
      }
   },
   "extends":[
      "config:base",
      "group:allNonMajor",
      ":semanticCommits"
   ],
   "git-submodules":{
      "enabled":true
   },
   "meteor":{
      "enabled":false
   },
   "rangeStrategy":"bump",
   "npm":{
      "commitMessageTopic":"{{prettyDepType}} {{depName}}"
   }
}
